earnix2_sdk-0.32.0.dist-info/METADATA
earnix2_sdk-0.32.0.dist-info/WHEEL
earnix2_sdk-0.32.0.dist-info/entry_points.txt
earnix2_sdk-0.32.0.dist-info/licenses/LICENSE
earnix2_sdk/__init__.py
earnix2_sdk/clients/__init__.py
earnix2_sdk/clients/admin/__init__.py
earnix2_sdk/clients/admin/api/__init__.py
earnix2_sdk/clients/admin/api_client.py
earnix2_sdk/clients/admin/api_response.py
earnix2_sdk/clients/admin/configuration.py
earnix2_sdk/clients/admin/exceptions.py
earnix2_sdk/clients/admin/models/__init__.py
earnix2_sdk/clients/admin/rest.py
earnix2_sdk/clients/data/__init__.py
earnix2_sdk/clients/data/api/__init__.py
earnix2_sdk/clients/data/api/data_table_service_api.py
earnix2_sdk/clients/data/api_client.py
earnix2_sdk/clients/data/api_response.py
earnix2_sdk/clients/data/configuration.py
earnix2_sdk/clients/data/exceptions.py
earnix2_sdk/clients/data/models/__init__.py
earnix2_sdk/clients/data/models/common_audit_properties.py
earnix2_sdk/clients/data/models/common_for_update_properties.py
earnix2_sdk/clients/data/models/common_properties.py
earnix2_sdk/clients/data/models/create_data_table_request.py
earnix2_sdk/clients/data/models/create_data_version_request.py
earnix2_sdk/clients/data/models/data_table_data_source_properties.py
earnix2_sdk/clients/data/models/data_table_response.py
earnix2_sdk/clients/data/models/data_table_version_properties.py
earnix2_sdk/clients/data/models/data_version_properties.py
earnix2_sdk/clients/data/models/data_version_response.py
earnix2_sdk/clients/data/models/export_part_result_pair_type.py
earnix2_sdk/clients/data/models/export_s3_job_part_result_properties.py
earnix2_sdk/clients/data/models/export_s3_job_part_status_properties.py
earnix2_sdk/clients/data/models/export_s3_part_properties.py
earnix2_sdk/clients/data/models/export_s3_part_response.py
earnix2_sdk/clients/data/models/get_export_s3_part_job_status_response.py
earnix2_sdk/clients/data/models/problem_detail.py
earnix2_sdk/clients/data/models/update_data_table_request.py
earnix2_sdk/clients/data/models/user.py
earnix2_sdk/clients/data/rest.py
earnix2_sdk/clients/imx/__init__.py
earnix2_sdk/clients/imx/api/__init__.py
earnix2_sdk-0.32.0.dist-info/RECORD
