Metadata-Version: 2.1
Name: earnix2-sdk
Version: 0.32.0
Summary: Earnix 2.0 SDK
Keywords: sdk,fintech,insurance,banking
Author-Email: "Earnix Ltd." <info@earnix.com>
License:                                  Apache License
Classifier: Topic :: Software Development :: Libraries :: Python Modules
Classifier: Intended Audience :: Developers
Classifier: Intended Audience :: Financial and Insurance Industry
Classifier: Intended Audience :: Science/Research
Classifier: Programming Language :: Python :: 3
Classifier: Programming Language :: Python :: 3.9
Classifier: Programming Language :: Python :: 3.10
Classifier: Programming Language :: Python :: 3.11
Classifier: Programming Language :: Python :: 3.12
Classifier: Programming Language :: Python :: 3.13
Project-URL: Homepage, https://earnix.com
Project-URL: Documentation, https://pypi.org/project/earnix2-sdk
Requires-Python: >=3.9
Requires-Dist: python-dateutil>=2.9.0.post0
Requires-Dist: typing-extensions>=4.12.2
Requires-Dist: urllib3>=2.2.3
Requires-Dist: pydantic>=2.9.2
Requires-Dist: pyjwt>=2.10.1
